pyvoting/ApprovalVoting.py
pyvoting/NormalizedScoreVoting.py
pyvoting/PluralityVoting.py
pyvoting/RankedChoiceVoting.py
pyvoting/STARVoting.py
pyvoting/ScoreVoting.py
pyvoting/StandardizedScoreVoting.py
pyvoting/TierListVoting.py
pyvoting/TieredPopularityVoting.py
pyvoting/Voting.py
pyvoting/__init__.py
pyvoting/main.py
pyvoting-1.0.1.dist-info/LICENCE
pyvoting-1.0.1.dist-info/METADATA
pyvoting-1.0.1.dist-info/WHEEL
pyvoting-1.0.1.dist-info/top_level.txt
pyvoting-1.0.1.dist-info/RECORD
