Metadata-Version: 2.1
Name: pyvoting
Version: 1.0.1
Summary: simulating elections with 9 choices of voting methods, including 4 I have invented
Author: Yichen Zhang
Author-email: zycrdfz@gmail.com
Keywords: python,vote,voting,election,approval voting,star voting,ranked choice voting,rcv,tier list
Classifier: Development Status :: 3 - Alpha
Classifier: Intended Audience :: Developers
Classifier: Programming Language :: Python :: 3
Classifier: Operating System :: Unix
Classifier: Operating System :: MacOS :: MacOS X
Classifier: Operating System :: Microsoft :: Windows
License-File: LICENCE
Requires-Dist: pandas
Requires-Dist: numpy
